PyMachineLearning/__init__.py
PyMachineLearning/evaluation.py
PyMachineLearning/metrics.py
PyMachineLearning/models.py
PyMachineLearning/plots.py
PyMachineLearning/preprocessing.py
PyMachineLearning/test.py
PyMachineLearning-0.0.23.dist-info/LICENSE
PyMachineLearning-0.0.23.dist-info/METADATA
PyMachineLearning-0.0.23.dist-info/WHEEL
PyMachineLearning-0.0.23.dist-info/top_level.txt
PyMachineLearning-0.0.23.dist-info/RECORD
